<annotation>
	<folder>XR_HUMERUS</folder>
	<filename>positive_2.png</filename>
	<path>D:\Documents\Faks\ETF\Master 2.0\object_detection_intro\resources\tf-object-detection\dataset\XR_HUMERUS\positive_2.png</path>
	<source>
		<database>Unknown</database>
	</source>
	<size>
		<width>512</width>
		<height>512</height>
		<depth>1</depth>
	</size>
	<segmented>0</segmented>
	<object>
		<name>implant</name>
		<pose>Unspecified</pose>
		<truncated>0</truncated>
		<difficult>0</difficult>
		<bndbox>
			<xmin>270</xmin>
			<ymin>38</ymin>
			<xmax>366</xmax>
			<ymax>175</ymax>
		</bndbox>
	</object>
</annotation>
