<annotation>
	<folder>train</folder>
	<filename>positive_121.png</filename>
	<path>D:\Documents\Faks\ETF\Master 2.0\other\MURA\generated\train\positive_121.png</path>
	<source>
		<database>Unknown</database>
	</source>
	<size>
		<width>420</width>
		<height>512</height>
		<depth>1</depth>
	</size>
	<segmented>0</segmented>
	<object>
		<name>implant</name>
		<pose>Unspecified</pose>
		<truncated>0</truncated>
		<difficult>0</difficult>
		<bndbox>
			<xmin>146</xmin>
			<ymin>50</ymin>
			<xmax>223</xmax>
			<ymax>198</ymax>
		</bndbox>
	</object>
</annotation>
