<annotation>
	<folder>train</folder>
	<filename>positive_414.png</filename>
	<path>D:\Documents\Faks\ETF\Master 2.0\other\MURA\generated\train\positive_414.png</path>
	<source>
		<database>Unknown</database>
	</source>
	<size>
		<width>512</width>
		<height>420</height>
		<depth>1</depth>
	</size>
	<segmented>0</segmented>
	<object>
		<name>implant</name>
		<pose>Unspecified</pose>
		<truncated>0</truncated>
		<difficult>0</difficult>
		<bndbox>
			<xmin>271</xmin>
			<ymin>143</ymin>
			<xmax>472</xmax>
			<ymax>188</ymax>
		</bndbox>
	</object>
</annotation>
